django_persian_currency/__init__.py
django_persian_currency/admin.py
django_persian_currency/apps.py
django_persian_currency/models.py
django_persian_currency/tests.py
django_persian_currency/views.py
django_persian_currency/templatetags/__init__.py
django_persian_currency/templatetags/iran_money_display.py
django_persian_currency-0.2.1.dist-info/METADATA
django_persian_currency-0.2.1.dist-info/WHEEL
django_persian_currency-0.2.1.dist-info/top_level.txt
django_persian_currency-0.2.1.dist-info/RECORD
