Metadata-Version: 2.4
Name: django_persian_currency
Version: 0.2.1
Summary: A Django app to work with Iranian currency.
Home-page: https://github.com/MohammadJavadRamezanpour/django_persian_currency
Author: Mohammad Javad
Author-email: ramezanpourmohammadjavad@gmail.com
Classifier: Framework :: Django
Classifier: Programming Language :: Python :: 3
Classifier: License :: OSI Approved :: MIT License
Classifier: Operating System :: OS Independent
Requires-Python: >=3.7
Dynamic: author
Dynamic: author-email
Dynamic: classifier
Dynamic: description
Dynamic: description-content-type
Dynamic: home-page
Dynamic: requires-python
Dynamic: summary
